LICENSE
README.md
setup.py
rainbond_python/__init__.py
rainbond_python/cli.py
rainbond_python/db_connect.py
rainbond_python/download.py
rainbond_python/error_handler.py
rainbond_python/parameter.py
rainbond_python/redis_connect.py
rainbond_python/tools.py
rainbond_python/verify_token.py
rainbond_python.egg-info/PKG-INFO
rainbond_python.egg-info/SOURCES.txt
rainbond_python.egg-info/dependency_links.txt
rainbond_python.egg-info/entry_points.txt
rainbond_python.egg-info/requires.txt
rainbond_python.egg-info/top_level.txt