Metadata-Version: 2.1
Name: rainbond-python
Version: 1.3.7
Summary: Rainbond python cloud native development base library
Home-page: https://github.com/hekaiyou/rainbond-python
Author: Kaiyou He
Author-email: hky0313@outlook.com
Keywords: rainbond python cloud native
License-File: LICENSE
